A1(verilog)/Q3/halfAdder.v
//Siddharth Singh and Chaitany Pandiya
//17CO146 and 17CO112
//Hello World program using Verilog
//14 October 2018
module halfAdder(
inputBit1,
inputBit2,
sum,
carry
);
input inputBit1,inputBit2;
output sum,carry;
assign sum=inputBit1^inputBit2;
assign carry=inputBit1&inputBit2;
endmodule

A1(verilog)/Q4/fullAdder.v
//Siddharth Singh and Chaitany Pandiya
//17CO146 and 17CO112
//Hello World program using Verilog
//14 October 2018
`include "halfAdder.v"
module fullAdder(
inputbit1,
inputbit2,
inputcarry,
sum,
carry
);
input inputbit1,inputbit2,inputcarry;
output sum,carry;
wire w1,w2,w3;
halfAdder ha1(inputbit1,inputbit2,w1,w2);
halfAdder ha2(w1,inputcarry,sum,w3);
or g1(carry,w2,w3);
endmodule

A1(verilog)/Q4/test_fullAdder.v
//Siddharth Singh and Chaitany Pandiya
//17CO146 and 17CO112
//Hello World program using Verilog
//14 October 2018
`timescale 1ns/100ps
`include "fullAdder.v"
module test_fullAdder;
reg rbit1=0,rbit2=0,rcarry;
wire wsum,wcarry;
fullAdder ins(
rbit1,
rbit2,
rcarry,
wsum,
wcarry
);
initial
begin
    $dumpfile("fullAdder.vcd");
    $dumpvars(0,test_fullAdder);
end
initial
begin
    rbit1=1'b0;
    rbit2=1'b0;
    rcarry=1'b0;
    #10;
    rbit1=1'b0;
    rbit2=1'b0;
    rcarry=1'b1;
    #10;
    rbit1=1'b0;
    rbit2=1'b1;
    rcarry=1'b0;
    #10;
    rbit1=1'b0;
    rbit2=1'b1;
    rcarry=1'b1;
    #10;
    rbit1=1'b1;
    rbit2=1'b0;
    rcarry=1'b0;
    #10;
    rbit1=1'b1;
    rbit2=1'b0;
    rcarry=1'b1;
    #10;
    rbit1=1'b1;
    rbit2=1'b1;
    rcarry=1'b0;
    #10;
    rbit1=1'b1;
    rbit2=1'b1;
    rcarry=1'b1;
    #10;
end
initial begin
$monitor("Time=%0d inputbit1=%b inputbit2=%b inputcarry=%b sum=%b carry=%b",$time,rbit1,rbit2,rcarry,wsum,wcarry);  //display result when a and b are added
#160 $finish;
end
endmodule

A1(verilog)/Q4/fullAdder.vcd
$date
	Mon Oct 15 22:32:36 2018
$end
$version
	Icarus Verilog
$end
$timescale
	100ps
$end
$scope module test_fullAdder $end
$var wire 1 ! wsum $end
$var wire 1 " wcarry $end
$var reg 1 # rbit1 $end
$var reg 1 $ rbit2 $end
$var reg 1 % rcarry $end
$scope module ins $end
$var wire 1 " carry $end
$var wire 1 # inputbit1 $end
$var wire 1 $ inputbit2 $end
$var wire 1 % inputcarry $end
$var wire 1 & w3 $end
$var wire 1 ' w2 $end
$var wire 1 ( w1 $end
$var wire 1 ! sum $end
$scope module ha1 $end
$var wire 1 ' carry $end
$var wire 1 # inputBit1 $end
$var wire 1 $ inputBit2 $end
$var wire 1 ( sum $end
$upscope $end
$scope module ha2 $end
$var wire 1 & carry $end
$var wire 1 ( inputBit1 $end
$var wire 1 % inputBit2 $end
$var wire 1 ! sum $end
$upscope $end
$upscope $end
$upscope $end
$enddefinitions $end
#0
$dumpvars
0(
0'
0&
0%
0$
0#
0"
0!
$end
#100
1!
1%
#200
1(
0%
1$
#300
1"
0!
1&
1%
#400
0"
1!
0&
0%
0$
1#
#500
1"
0!
1&
1%
#600
0&
0(
1'
0%
1$
#700
1!
1%
