A1(verilog)/Q6/dlatch.v
module d_latch(Q,Qn,G,D);
   output Q,Qn;
   input G,D;   
   
   wire Dn,D1,Dn1;
   
   not(Dn,D);
   nand(D1,G, D);
   nand(Dn1,G, Dn);
   nand(Q,D1,Qn);
   nand(Qn,Dn1,Q);
endmodule

A1(verilog)/Q6/dffms.v
//submitted by Siddharth Singh(17CO146) & Chaitany Pandiya(17C0112)
`include "dlatch.v"
module dflipflop(Qms,Qnms,C,Dms);
   output Qms,Qnms;
   input C,Dms;
   
   wire y,yn;
	
	d_latch master(y,yn,C,Dms);   //input master latch
   	d_latch slave(Qms,Qnms,~C,y);   //input slave latch
	
endmodule

A1(verilog)/Q6/dffbehav.v
//submitted by Siddharth Singh(17CO146) & Chaitany Pandiya(17C0112)
module d(q,q1,d,c);
output q,q1;
 input d,c;
 reg q,q1;
	initial 
	   begin
		   q=1'b0; q1=1'b1;//initial value of q qnd q1
	   end
	always @ (posedge c)//always change at posedge of clock
	   begin 
		 q=d;
		 q1= ~d;
	   end
endmodule

A1(verilog)/Q6/dffsr.v
//submitted by Siddharth Singh(17CO146) & Chaitany Pandiya(17C0112)
module d1(Q,Qn,D,C);
	input D,C;
	output Q,Qn;
	wire S,R,w1,w2,w3;
	nand(S,C,w1);//Referred diagram in the book 
	nand(R,C,S,w2);
	nand(w1,w2,S);
	nand(w2,R,D);
	nand(Q,S,Qn);
	nand(Qn,R,Q);
endmodule

A1(verilog)/Q6/t_dflipflop.v
//submitted by Siddharth Singh(17CO146) & Chaitany Pandiya(17C0112)
`include "dffsr.v"
`include "dffbehav.v"
`include "dffms.v"
`timescale 1ns/1ps
module testdff;
wire Q,Qn,Qms,Qnms,Qsr,Qnsr;
reg D,C,Dms,Dsr;

d1 sr(Qsr,Qnsr,Dsr,C);
d behav(Q,Qn,D,C);
dflipflop MS(Qms,Qnms,C,Dms);
initial 
begin
		$dumpfile("dff.vcd");    //gtkwave production
		$dumpvars(0, testdff);
		C=0;             //clk set
		forever #1 C=~C;
end
initial 
begin                                //value of d set at regular interval and displayed
		D=0;Dms=0;Dsr=0;
		$monitor("clock=%b, d=%b, q=%b",C,D,Q);
	#8;
		D=1;Dms=1;Dsr=1;
		$monitor("clock=%b, d=%b, q=%b",C,D,Q);
	#8;
		D=0;Dms=0;Dsr=0;
		$monitor("clock=%b, d=%b, q=%b",C,D,Q);
	#8;
		D=1;Dms=1;Dsr=1;
		$monitor("clock=%b, d=%b, q=%b",C,D,Q);
                
end
initial #30 $finish;
endmodule

A1(verilog)/Q6/dff.vcd
$date
	Mon Oct 15 22:00:24 2018
$end
$version
	Icarus Verilog
$end
$timescale
	1ps
$end
$scope module testdff $end
$var wire 1 ! Qsr $end
$var wire 1 " Qnsr $end
$var wire 1 # Qnms $end
$var wire 1 $ Qn $end
$var wire 1 % Qms $end
$var wire 1 & Q $end
$var reg 1 ' C $end
$var reg 1 ( D $end
$var reg 1 ) Dms $end
$var reg 1 * Dsr $end
$scope module MS $end
$var wire 1 ' C $end
$var wire 1 ) Dms $end
$var wire 1 + yn $end
$var wire 1 , y $end
$var wire 1 # Qnms $end
$var wire 1 % Qms $end
$scope module master $end
$var wire 1 ) D $end
$var wire 1 - D1 $end
$var wire 1 . Dn $end
$var wire 1 / Dn1 $end
$var wire 1 ' G $end
$var wire 1 , Q $end
$var wire 1 + Qn $end
$upscope $end
$scope module slave $end
$var wire 1 , D $end
$var wire 1 0 D1 $end
$var wire 1 1 Dn $end
$var wire 1 2 Dn1 $end
$var wire 1 3 G $end
$var wire 1 % Q $end
$var wire 1 # Qn $end
$upscope $end
$upscope $end
$scope module behav $end
$var wire 1 ' c $end
$var wire 1 ( d $end
$var reg 1 & q $end
$var reg 1 $ q1 $end
$upscope $end
$scope module sr $end
$var wire 1 ' C $end
$var wire 1 * D $end
$var wire 1 ! Q $end
$var wire 1 " Qn $end
$var wire 1 4 R $end
$var wire 1 5 S $end
$var wire 1 6 w1 $end
$var wire 1 7 w2 $end
$upscope $end
$upscope $end
$enddefinitions $end
#0
$dumpvars
17
06
15
14
13
x2
x1
x0
1/
1.
1-
x,
x+
0*
0)
0(
0'
0&
x%
1$
x#
x"
x!
$end
#1000
11
0,
0!
10
12
1+
1"
03
0/
04
1'
#2000
0%
1#
02
13
1/
14
0'
#3000
12
03
0/
04
1'
#4000
02
13
1/
14
0'
#5000
12
03
0/
04
1'
#6000
02
13
1/
14
0'
#7000
12
03
0/
04
1'
#8000
16
02
07
13
1/
14
0.
0'
1*
1)
1(
#9000
0+
01
0"
12
1,
1!
03
0-
0$
1&
05
1'
#10000
0#
1%
00
13
1-
15
0'
#11000
10
03
0-
05
1'
#12000
00
13
1-
15
0'
#13000
10
03
0-
05
1'
#14000
00
13
1-
15
0'
#15000
10
03
0-
05
1'
#16000
00
06
13
15
17
1.
1-
0'
0*
0)
0(
#17000
11
0,
0!
10
1+
1"
03
0/
1$
0&
04
1'
#18000
0%
1#
02
13
1/
14
0'
#19000
12
03
0/
04
1'
#20000
02
13
1/
14
0'
#21000
12
03
0/
04
1'
#22000
02
13
1/
14
0'
#23000
12
03
0/
04
1'
#24000
16
02
07
13
1/
14
0.
0'
1*
1)
1(
#25000
0+
01
0"
12
1,
1!
03
0-
0$
1&
05
1'
#26000
0#
1%
00
13
1-
15
0'
#27000
10
03
0-
05
1'
#28000
00
13
1-
15
0'
#29000
10
03
0-
05
1'
#30000
00
13
1-
15
0'
