A1(verilog)/Q2/decoder.v
//Siddharth Singh and Chaitany Pandiya
//17CO146
//4X16 decoder using Verilog
//14 October 2018
module decoder(
dec,a,b,c,d,enable
);
output [0:15] dec;       //16-bit output
input      a,b,c,d;      //4-bit input with enable
input enable;
wire  anot,bnot,cnot,dnot,enablenot;
not (anot,a),            //gate level implementation
(bnot,b),
(cnot,c),
(dnot,d),
(enablenot,enable);
nand
(dec[0],anot,bnot,cnot,dnot,enablenot),
(dec[1],anot,bnot,cnot,d,enablenot),
(dec[2],anot,bnot,c,dnot,enablenot),
(dec[3],anot,bnot,c,d,enablenot),
(dec[4],anot,b,cnot,dnot,enablenot),
(dec[5],anot,b,cnot,d,enablenot),
(dec[6],anot,b,c,dnot,enablenot),
(dec[7],anot,b,c,d,enablenot),
(dec[8],a,bnot,cnot,dnot,enablenot),
(dec[9],a,bnot,cnot,d,enablenot),
(dec[10],a,bnot,c,dnot,enablenot),
(dec[11],a,bnot,c,d,enablenot),
(dec[12],a,b,cnot,dnot,enablenot),
(dec[13],a,b,cnot,d,enablenot),
(dec[14],a,b,c,dnot,enablenot),
(dec[15],a,b,c,d,enablenot);
endmodule

A1(verilog)/Q2/test_decoder.v
//Siddharth Singh and Chaitany Pandiya
//17CO146
//4X16 decoder testbench using Verilog
//14 October 2018
`timescale 1ns/100ps
`include "decoder.v"
module test_decoder;
reg ra,rb,rc,rd,ren;
wire [0:15] rdec;
decoder ins(rdec,ra,rb,rc,rd,ren);  //instance of decoder module
initial
begin
    $dumpfile("decoder.vcd");        //to create gtkwave
    $dumpvars(0,test_decoder);
end
initial
begin
    ra=1'b0;
    rb=1'b0;
    rc=1'b0;
    rd=1'b0;
    ren=1'b0;
    #5;
    ra=1'b0;
    rb=1'b0;
    rc=1'b0;
    rd=1'b1;
    ren=1'b0;
    #5;
    ra=1'b0;
    rb=1'b0;
    rc=1'b1;
    rd=1'b0;
    ren=1'b0;
    #5;
    ra=1'b0;
    rb=1'b0;
    rc=1'b1;
    rd=1'b1;
    ren=1'b0;
    #5;
    ra=1'b0;
    rb=1'b1;
    rc=1'b0;
    rd=1'b0;
    ren=1'b0;
    #5;
    ra=1'b0;
    rb=1'b1;
    rc=1'b0;
    rd=1'b1;
    ren=1'b0;
    #5;
    ra=1'b0;
    rb=1'b1;
    rc=1'b1;
    rd=1'b0;
    ren=1'b0;
    #5;
    ra=1'b0;
    rb=1'b1;
    rc=1'b1;
    rd=1'b1;
    ren=1'b0;
    #5;
    ra=1'b1;
    rb=1'b0;
    rc=1'b0;
    rd=1'b0;
    ren=1'b0;
    #5;
    ra=1'b1;
    rb=1'b0;
    rc=1'b0;
    rd=1'b1;
    ren=1'b0;
    #5;
    ra=1'b1;
    rb=1'b0;
    rc=1'b1;
    rd=1'b0;
    ren=1'b0;
    #5;
    ra=1'b1;
    rb=1'b0;
    rc=1'b1;
    rd=1'b1;
    ren=1'b0;
    #5;
    ra=1'b1;
    rb=1'b1;
    rc=1'b0;
    rd=1'b0;
    ren=1'b0;
    #5;
    ra=1'b1;
    rb=1'b1;
    rc=1'b0;
    rd=1'b1;
    ren=1'b0;
    #5;
    ra=1'b1;
    rb=1'b1;
    rc=1'b1;
    rd=1'b0;
    ren=1'b0;
    #5;
    ra=1'b1;
    rb=1'b1;
    rc=1'b1;
    rd=1'b1;
    ren=1'b0;
    #5;

end
initial begin              //displaying desired values
	$monitor("input=%b%b%b%b output=%b%b%b%b%b%b%b%b%b%b%b%b%b%b%b",ra,rb,rc,rd,rdec[15],rdec[14],rdec[13],rdec[12],rdec[11],rdec[10],rdec[9],rdec[8],rdec[7],rdec[6],rdec[5],rdec[4],rdec[3],rdec[2],rdec[1],rdec[0]);

	#300 $finish;        //after every 20 ns input changes and there are 15 combination of input so after 300 ns program terminates
end
endmodule

A1(verilog)/Q2/decoder.vcd
$date
	Mon Oct 15 22:12:30 2018
$end
$version
	Icarus Verilog
$end
$timescale
	100ps
$end
$scope module test_decoder $end
$var wire 16 ! rdec [0:15] $end
$var reg 1 " ra $end
$var reg 1 # rb $end
$var reg 1 $ rc $end
$var reg 1 % rd $end
$var reg 1 & ren $end
$scope module ins $end
$var wire 1 " a $end
$var wire 1 ' anot $end
$var wire 1 # b $end
$var wire 1 ( bnot $end
$var wire 1 $ c $end
$var wire 1 ) cnot $end
$var wire 1 % d $end
$var wire 1 * dnot $end
$var wire 1 & enable $end
$var wire 1 + enablenot $end
$var wire 16 , dec [0:15] $end
$upscope $end
$upscope $end
$enddefinitions $end
#0
$dumpvars
b111111111111111 ,
1+
1*
1)
1(
1'
0&
0%
0$
0#
0"
b111111111111111 !
$end
#50
b1011111111111111 !
b1011111111111111 ,
0*
1%
#100
b1101111111111111 !
b1101111111111111 ,
1*
0)
0%
1$
#150
b1110111111111111 !
b1110111111111111 ,
0*
1%
#200
b1111011111111111 !
b1111011111111111 ,
1*
1)
0(
0%
0$
1#
#250
b1111101111111111 !
b1111101111111111 ,
0*
1%
#300
b1111110111111111 !
b1111110111111111 ,
1*
0)
0%
1$
#350
b1111111011111111 !
b1111111011111111 ,
0*
1%
#400
b1111111101111111 !
b1111111101111111 ,
1*
1)
1(
0'
0%
0$
0#
1"
#450
b1111111110111111 !
b1111111110111111 ,
0*
1%
#500
b1111111111011111 !
b1111111111011111 ,
1*
0)
0%
1$
#550
b1111111111101111 !
b1111111111101111 ,
0*
1%
#600
b1111111111110111 !
b1111111111110111 ,
1*
1)
0(
0%
0$
1#
#650
b1111111111111011 !
b1111111111111011 ,
0*
1%
#700
b1111111111111101 !
b1111111111111101 ,
1*
0)
0%
1$
#750
b1111111111111110 !
b1111111111111110 ,
0*
1%
