A1(verilog)/Q2/encoder.v
//Siddharth Singh and Chaitany Pandiya
//17CO146
//16X4 encoder using Verilog
//14 October 2018
module encoder(
a,d,en
);
output [0:3] a;
input [0:15] d;
input en;
wire w1,w2,w3,w4;
or
(w1,d[8],d[9],d[10],d[11],d[12],d[13],d[14],d[15]),
(w2,d[4],d[5],d[6],d[7],d[12],d[13],d[14],d[15]),
(w3,d[2],d[3],d[6],d[7],d[10],d[11],d[14],d[15]),
(w4,d[1],d[3],d[5],d[7],d[9],d[11],d[13],d[15]);
and
(a[3],w1,en),
(a[2],w2,en),
(a[1],w3,en),
(a[0],w4,en);
endmodule

A1(verilog)/Q2/test_encoder.v
//Siddharth Singh and Chaitany Pandiya
//17CO146
//16X4 encoder testbench using Verilog
//14 October 2018
`timescale 1ns/100ps
`include "encoder.v"
module test_encoder;
wire [0:3] a;
reg [0:15] d;
reg en;
encoder ins(a,d,en);
integer i;
initial
begin
  $dumpfile("encoder.vcd");           //to create gtkwave
  $dumpvars(0,test_encoder);
end
initial
begin
  en=1'b1;
for(i=0;i<=15;i++)
      begin
          d=0;
          d[i]=1;
        #20;
      end
end
initial begin              //displaying desired values
	$monitor("input=%b%b%b%b%b%b%b%b%b%b%b%b%b%b%b%b output=%b%b%b%b",d[15],d[14],d[13],d[12],d[11],d[10],d[9],d[8],d[7],d[6],d[5],d[4],d[3],d[2],d[1],d[0],a[3],a[2],a[1],a[0]);

#300 $finish;        //after every 20 ns input changes and there are 15 combination of input so after 300 ns program terminates
end
endmodule

A1(verilog)/Q2/encoder.vcd
$date
	Mon Oct 15 22:12:03 2018
$end
$version
	Icarus Verilog
$end
$timescale
	100ps
$end
$scope module test_encoder $end
$var wire 4 ! a [0:3] $end
$var reg 16 " d [0:15] $end
$var reg 1 # en $end
$var integer 32 $ i [31:0] $end
$scope module ins $end
$var wire 16 % d [0:15] $end
$var wire 1 # en $end
$var wire 1 & w1 $end
$var wire 1 ' w2 $end
$var wire 1 ( w3 $end
$var wire 1 ) w4 $end
$var wire 4 * a [0:3] $end
$upscope $end
$upscope $end
$enddefinitions $end
#0
$dumpvars
b0 *
0)
0(
0'
0&
b1000000000000000 %
b0 $
1#
b1000000000000000 "
b0 !
$end
#200
b1000 !
b1000 *
1)
b100000000000000 "
b100000000000000 %
b1 $
#400
b100 !
b100 *
1(
0)
b10000000000000 "
b10000000000000 %
b10 $
#600
b1100 !
b1100 *
1)
b1000000000000 "
b1000000000000 %
b11 $
#800
b10 !
b10 *
1'
0(
0)
b100000000000 "
b100000000000 %
b100 $
#1000
b1010 !
b1010 *
1)
b10000000000 "
b10000000000 %
b101 $
#1200
b110 !
b110 *
1(
0)
b1000000000 "
b1000000000 %
b110 $
#1400
b1110 !
b1110 *
1)
b100000000 "
b100000000 %
b111 $
#1600
b1 !
b1 *
1&
0'
0(
0)
b10000000 "
b10000000 %
b1000 $
#1800
b1001 !
b1001 *
1)
b1000000 "
b1000000 %
b1001 $
#2000
b101 !
b101 *
1(
0)
b100000 "
b100000 %
b1010 $
#2200
b1101 !
b1101 *
1)
b10000 "
b10000 %
b1011 $
#2400
b11 !
b11 *
1'
0(
0)
b1000 "
b1000 %
b1100 $
#2600
b1011 !
b1011 *
1)
b100 "
b100 %
b1101 $
#2800
b111 !
b111 *
1(
0)
b10 "
b10 %
b1110 $
#3000
b1111 !
b1111 *
1)
b1 "
b1 %
b1111 $
